odoo10_addon_account_invoice_import_factur_x-10.0.1.0.0.99.dev26-py2.7-nspkg.pth
odoo/addons/account_invoice_import_factur-x/README.rst
odoo/addons/account_invoice_import_factur-x/__init__.py
odoo/addons/account_invoice_import_factur-x/__manifest__.py
odoo/addons/account_invoice_import_factur-x/demo/demo_data.xml
odoo/addons/account_invoice_import_factur-x/i18n/account_invoice_import_factur-x.pot
odoo/addons/account_invoice_import_factur-x/i18n/de.po
odoo/addons/account_invoice_import_factur-x/i18n/es.po
odoo/addons/account_invoice_import_factur-x/i18n/fr.po
odoo/addons/account_invoice_import_factur-x/i18n/sl.po
odoo/addons/account_invoice_import_factur-x/static/description/icon.png
odoo/addons/account_invoice_import_factur-x/tests/__init__.py
odoo/addons/account_invoice_import_factur-x/tests/test_facturx.py
odoo/addons/account_invoice_import_factur-x/tests/files/Factur-X_BASIC-1.xml
odoo/addons/account_invoice_import_factur-x/tests/files/Factur-X_MINIMUM-1.xml
odoo/addons/account_invoice_import_factur-x/tests/files/ZUGFeRD_1p0_BASIC_Einfach.pdf
odoo/addons/account_invoice_import_factur-x/tests/files/ZUGFeRD_1p0_BASIC_Rechnungskorrektur.pdf
odoo/addons/account_invoice_import_factur-x/tests/files/ZUGFeRD_1p0_COMFORT_Einfach.pdf
odoo/addons/account_invoice_import_factur-x/tests/files/ZUGFeRD_1p0_COMFORT_Einfach.pdf-ZUGFeRD-invoice.xml
odoo/addons/account_invoice_import_factur-x/tests/files/ZUGFeRD_1p0_COMFORT_Haftpflichtversicherung_Versicherungssteuer.pdf
odoo/addons/account_invoice_import_factur-x/tests/files/ZUGFeRD_1p0_COMFORT_Kraftfahrversicherung_Bruttopreise.pdf
odoo/addons/account_invoice_import_factur-x/tests/files/ZUGFeRD_1p0_COMFORT_Rabatte.pdf
odoo/addons/account_invoice_import_factur-x/tests/files/ZUGFeRD_1p0_COMFORT_Rechnungskorrektur.pdf
odoo/addons/account_invoice_import_factur-x/tests/files/ZUGFeRD_1p0_COMFORT_SEPA_Prenotification.pdf
odoo10_addon_account_invoice_import_factur_x-10.0.1.0.0.99.dev26.dist-info/METADATA
odoo10_addon_account_invoice_import_factur_x-10.0.1.0.0.99.dev26.dist-info/RECORD
odoo10_addon_account_invoice_import_factur_x-10.0.1.0.0.99.dev26.dist-info/WHEEL
odoo10_addon_account_invoice_import_factur_x-10.0.1.0.0.99.dev26.dist-info/namespace_packages.txt
odoo10_addon_account_invoice_import_factur_x-10.0.1.0.0.99.dev26.dist-info/top_level.txt
